LICENSE
README.md
fv.py
pyproject.toml
c4ffein_fv.egg-info/PKG-INFO
c4ffein_fv.egg-info/SOURCES.txt
c4ffein_fv.egg-info/dependency_links.txt
c4ffein_fv.egg-info/top_level.txt