Metadata-Version: 2.1
Name: c4ffein-fv
Version: 0.0.1
Summary: KISS Python e2e encrypted FileVault based on gpg
Author-email: c4ffein <c4ffein@gmail.com>
Project-URL: Homepage, https://github.com/c4ffein/fv
Project-URL: Issues, https://github.com/c4ffein/fv
Classifier: Programming Language :: Python :: 3
Classifier: License :: OSI Approved :: MIT License
Classifier: Operating System :: OS Independent
Requires-Python: >=3.8
License-File: LICENSE
